youtube_download_cli/__init__.py
youtube_download_cli/command_line.py
youtube_download_cli-0.0.0.3.dist-info/LICENSE.txt
youtube_download_cli-0.0.0.3.dist-info/METADATA
youtube_download_cli-0.0.0.3.dist-info/WHEEL
youtube_download_cli-0.0.0.3.dist-info/entry_points.txt
youtube_download_cli-0.0.0.3.dist-info/top_level.txt
youtube_download_cli-0.0.0.3.dist-info/RECORD
