Metadata-Version: 2.1
Name: youtube-download-cli
Version: 0.0.0.3
Home-page: https://github.com/jpleorx/youtube-download-cli
Download-URL: https://pypi.org/project/youtube-download-cli/
Author: Leo Ertuna
Author-email: leo.ertuna@gmail.com
License: Creative Commons Attribution-NonCommercial-NoDerivatives 4.0 International Public License
License-File: LICENSE.txt
Requires-Dist: argparse
Requires-Dist: colorama
Requires-Dist: pytube
Requires-Dist: moviepy
